base64_encoder/__init__.py
base64_encoder/encoder.py
base64_encoder_cli-1.0.0.dist-info/METADATA
base64_encoder_cli-1.0.0.dist-info/WHEEL
base64_encoder_cli-1.0.0.dist-info/entry_points.txt
base64_encoder_cli-1.0.0.dist-info/top_level.txt
base64_encoder_cli-1.0.0.dist-info/RECORD
