Metadata-Version: 2.4
Name: base64-encoder-cli
Version: 1.0.0
Summary: Interactive Base64 encoding/decoding utility
Author: Lucy
Requires-Python: >=3.6
